[
{
    "model": "auth.user",
    "pk": 1,
    "fields": {
        "password": "pbkdf2_sha256$1000000$H6q8MxOErtTD85Cqltxke2$u8IVBXlncnJDSiWHaykGDm5fQig0DZFYViqJeXa/KcI=",
        "last_login": null,
        "is_superuser": true,
        "username": "adam",
        "first_name": "",
        "last_name": "",
        "email": "adam.hruska.s@gyarab.cz",
        "is_staff": true,
        "is_active": true,
        "date_joined": "2025-11-21T20:40:09.124Z",
        "groups": [],
        "user_permissions": []
    }
},

{
    "model": "auth.user",
    "pk": 2,
    "fields": {
        "password": "pbkdf2_sha256$1000000$pP3kAxn2sHKBGwRdKS5ELY$wzydW5ICyx3jGWDkk2tQnLFerYepJiQFBELcwqVCVuw=",
        "last_login": null,
        "is_superuser": true,
        "username": "admin-adam",
        "first_name": "",
        "last_name": "",
        "email": "adam.hruska.s@gyarab.cz",
        "is_staff": true,
        "is_active": true,
        "date_joined": "2025-12-02T18:50:35.710Z",
        "groups": [],
        "user_permissions": []
    }
}
]
